serial_grid/__init__.py
serial_grid/serial_grid.py
serial_visualisation-1.2.0.dist-info/LICENSE
serial_visualisation-1.2.0.dist-info/METADATA
serial_visualisation-1.2.0.dist-info/WHEEL
serial_visualisation-1.2.0.dist-info/top_level.txt
serial_visualisation-1.2.0.dist-info/RECORD
