Metadata-Version: 2.1
Name: serial-visualisation
Version: 1.2.0
Summary: A package for visualisation of serial data in a grid.
Home-page: https://github.com/ES-Alexander/serial-visualisation
Author: ES-Alexander
Author-email: sandman.esalexander@gmail.com
License: UNKNOWN
Platform: UNKNOWN
Classifier: Programming Language :: Python :: 3
Classifier: License :: OSI Approved :: MIT License
Classifier: Operating System :: OS Independent
Requires-Python: >=3.6
Requires-Dist: numpy
Requires-Dist: opencv-python
Requires-Dist: pyserial
